robo_bot_cli/__init__.py
robo_bot_cli/__main__.py
robo_bot_cli/main.py
robo_bot_cli/commands/__init__.py
robo_bot_cli/commands/clean.py
robo_bot_cli/commands/connect.py
robo_bot_cli/commands/deploy.py
robo_bot_cli/commands/diff.py
robo_bot_cli/commands/environment.py
robo_bot_cli/commands/interactive.py
robo_bot_cli/commands/login.py
robo_bot_cli/commands/logout.py
robo_bot_cli/commands/logs.py
robo_bot_cli/commands/package.py
robo_bot_cli/commands/remove.py
robo_bot_cli/commands/run.py
robo_bot_cli/commands/seed.py
robo_bot_cli/commands/shell.py
robo_bot_cli/commands/start.py
robo_bot_cli/commands/status.py
robo_bot_cli/commands/stop.py
robo_bot_cli/commands/stories.py
robo_bot_cli/commands/test.py
robo_bot_cli/commands/train.py
robo_bot_cli/config/__init__.py
robo_bot_cli/config/bot_manifest.py
robo_bot_cli/config/environment_constants.py
robo_bot_cli/config/environment_settings.py
robo_bot_cli/config/tool_settings.py
robo_bot_cli/config/store/__init__.py
robo_bot_cli/config/store/utils.py
robo_bot_cli/initial_structure/__init__.py
robo_bot_cli/initial_structure/resources_path.py
robo_bot_cli/initial_structure/initial_project/.botignore
robo_bot_cli/initial_structure/initial_project/__init__.py
robo_bot_cli/initial_structure/initial_project/credentials.yml
robo_bot_cli/initial_structure/initial_project/endpoints.yml
robo_bot_cli/initial_structure/initial_project/requirements.txt
robo_bot_cli/initial_structure/initial_project/actions/action.py
robo_bot_cli/initial_structure/initial_project/actions/action_parlai_fallback.py
robo_bot_cli/initial_structure/initial_project/custom/components/exact_match_classifier/exact_match_classifier.py
robo_bot_cli/initial_structure/initial_project/custom/components/spacy_nlp/spacy_nlp_neuralcoref.py
robo_bot_cli/initial_structure/initial_project/custom/components/spacy_nlp/spacy_tokenizer_neuralcoref.py
robo_bot_cli/initial_structure/initial_project/custom/policies/language_detection/lang_change_policy.py
robo_bot-0.1.3.dist-info/LICENSE
robo_bot-0.1.3.dist-info/METADATA
robo_bot-0.1.3.dist-info/WHEEL
robo_bot-0.1.3.dist-info/entry_points.txt
robo_bot-0.1.3.dist-info/top_level.txt
robo_bot-0.1.3.dist-info/RECORD
