Metadata-Version: 2.1
Name: robo-bot
Version: 0.1.3
Summary: A command line tool to create, manage and deploy Rasa chatbots.
Home-page: https://github.com/robo-ai/roboai-python-cli
Author: ROBO.AI
Author-email: info@robo-ai.com
License: MIT
Platform: UNKNOWN
Classifier: Programming Language :: Python :: 3.7
Classifier: Operating System :: OS Independent
Requires-Dist: click
Requires-Dist: colorama
Requires-Dist: cursor
Requires-Dist: halo
Requires-Dist: polling
Requires-Dist: pyfiglet
Requires-Dist: termcolor
Requires-Dist: robo-ai
Requires-Dist: rasa (==1.10.0)
Requires-Dist: pandas
Requires-Dist: openpyxl
Requires-Dist: pytablewriter
Requires-Dist: xlsxwriter
